dataknobs_utils/__init__.py
dataknobs_utils/elasticsearch_utils.py
dataknobs_utils/emoji_utils.py
dataknobs_utils/file_utils.py
dataknobs_utils/json_extractor.py
dataknobs_utils/json_utils.py
dataknobs_utils/llm_utils.py
dataknobs_utils/pandas_utils.py
dataknobs_utils/py.typed
dataknobs_utils/requests_utils.py
dataknobs_utils/resource_utils.py
dataknobs_utils/sql_utils.py
dataknobs_utils/stats_utils.py
dataknobs_utils/subprocess_utils.py
dataknobs_utils/sys_utils.py
dataknobs_utils/xml_utils.py
dataknobs_utils-1.2.2.dist-info/METADATA
dataknobs_utils-1.2.2.dist-info/WHEEL
dataknobs_utils-1.2.2.dist-info/RECORD
