Metadata-Version: 2.4
Name: dataknobs-utils
Version: 1.2.2
Summary: Utility functions for dataknobs packages
Author-email: Spence Koehler <KoehlerSB747@gmail.com>
Requires-Python: >=3.10
Requires-Dist: beautifulsoup4>=4.9.0
Requires-Dist: dataknobs-common>=1.0.0
Requires-Dist: dataknobs-structures>=1.0.0
Requires-Dist: json-stream>=2.3.0
Requires-Dist: lxml>=4.6.0
Requires-Dist: nltk>=3.7
Requires-Dist: pandas>=1.3.0
Requires-Dist: psycopg2-binary>=2.8.6
Requires-Dist: python-dotenv>=0.19.0
Requires-Dist: python3-nmap>=1.5.0
Requires-Dist: requests>=2.25.0
Requires-Dist: scikit-learn>=1.0.0
